Joywata/__init__ copy.py
Joywata/__init__.py
Joywata/console.py
Joywata/images_filtering.py
Joywata/dockercmd/__init__.py
Joywata/dockercmd/docker_run_cpu.sh
Joywata/dockercmd/docker_run_gpu.sh
Joywata-0.0.7.5.dist-info/METADATA
Joywata-0.0.7.5.dist-info/WHEEL
Joywata-0.0.7.5.dist-info/entry_points.txt
Joywata-0.0.7.5.dist-info/top_level.txt
Joywata-0.0.7.5.dist-info/RECORD
