Metadata-Version: 2.1
Name: Joywata
Version: 0.0.7.5
Summary: wata tools
Home-page: 
Author: wangtao
Author-email: 1083719817@qq.com
Maintainer: wangtao
Maintainer-email: 1083719817@qq.com
License: MIT License
Platform: Windows
Platform: Linux
Classifier: Development Status :: 3 - Alpha
Classifier: Intended Audience :: Developers
Classifier: Topic :: Software Development :: Build Tools
Classifier: License :: OSI Approved :: MIT License
Classifier: Programming Language :: Python :: 3
Requires-Dist: tabulate
